xl_dlframe/xl_dlframe.py
xl_dlframe-0.0.1.dist-info/METADATA
xl_dlframe-0.0.1.dist-info/WHEEL
xl_dlframe-0.0.1.dist-info/top_level.txt
xl_dlframe-0.0.1.dist-info/RECORD
